iceberg/__init__.py
iceberg/api/__init__.py
iceberg/api/append_files.py
iceberg/api/combined_scan_task.py
iceberg/api/data_file.py
iceberg/api/data_operations.py
iceberg/api/delete_files.py
iceberg/api/expire_snapshots.py
iceberg/api/file_format.py
iceberg/api/file_scan_task.py
iceberg/api/files.py
iceberg/api/filterable.py
iceberg/api/filtered_snapshot.py
iceberg/api/manifest_file.py
iceberg/api/metrics.py
iceberg/api/overwrite_files.py
iceberg/api/partition_field.py
iceberg/api/partition_spec.py
iceberg/api/pending_update.py
iceberg/api/replace_partitions.py
iceberg/api/rewrite_files.py
iceberg/api/rollback.py
iceberg/api/scan_task.py
iceberg/api/schema.py
iceberg/api/snapshot.py
iceberg/api/snapshot_iterable.py
iceberg/api/struct_like.py
iceberg/api/table.py
iceberg/api/table_scan.py
iceberg/api/tables.py
iceberg/api/transaction.py
iceberg/api/update_properties.py
iceberg/api/update_schema.py
iceberg/api/expressions/__init__.py
iceberg/api/expressions/binder.py
iceberg/api/expressions/evaluator.py
iceberg/api/expressions/expression.py
iceberg/api/expressions/expression_parser.py
iceberg/api/expressions/expressions.py
iceberg/api/expressions/inclusive_manifest_evaluator.py
iceberg/api/expressions/inclusive_metrics_evaluator.py
iceberg/api/expressions/literals.py
iceberg/api/expressions/predicate.py
iceberg/api/expressions/projections.py
iceberg/api/expressions/reference.py
iceberg/api/expressions/residual_evaluator.py
iceberg/api/expressions/strict_metrics_evaluator.py
iceberg/api/expressions/term.py
iceberg/api/expressions/transform.py
iceberg/api/expressions/java_variables/__init__.py
iceberg/api/io/__init__.py
iceberg/api/io/closeable_group.py
iceberg/api/io/closeable_iterable.py
iceberg/api/io/delegating_input_stream.py
iceberg/api/io/delegating_output_stream.py
iceberg/api/io/file_appender.py
iceberg/api/io/input_file.py
iceberg/api/io/output_file.py
iceberg/api/io/position_output_stream.py
iceberg/api/io/seekable_input_stream.py
acryl_iceberg_legacy-0.0.4.dist-info/METADATA
acryl_iceberg_legacy-0.0.4.dist-info/WHEEL
acryl_iceberg_legacy-0.0.4.dist-info/top_level.txt
acryl_iceberg_legacy-0.0.4.dist-info/RECORD
