Metadata-Version: 2.1
Name: acryl-iceberg-legacy
Version: 0.0.4
Summary: Acryl maintained copy of Iceberg Python bindings. Iceberg is a new table format for storing large, slow-moving tabular data
Home-page: https://github.com/acryldata/py-iceberg
Author-email: datahub@acryl.io
Maintainer: Acryl Data
License: Apache License 2.0
Keywords: iceberg
Classifier: License :: OSI Approved :: Apache Software License
Classifier: Programming Language :: Python :: 3.7
Classifier: Programming Language :: Python :: 3.8
Classifier: Programming Language :: Python :: 3.9
Requires-Python: >=3.7
Requires-Dist: botocore
Requires-Dist: boto3
Requires-Dist: fastavro (>=1.3.2<1.4.0)
Requires-Dist: hmsclient (==0.1.1)
Requires-Dist: mmh3
Requires-Dist: pyparsing (>=2.4.7<2.5.0)
Requires-Dist: python-dateutil
Requires-Dist: pytz
Requires-Dist: requests
Requires-Dist: retrying
Requires-Dist: pandas
Requires-Dist: pyarrow (>=6.0.1)
Requires-Dist: azure-storage-file-datalake
Requires-Dist: azure-identity
Provides-Extra: dev
Requires-Dist: tox-travis (==0.12) ; extra == 'dev'
Requires-Dist: virtualenv (<20.0.0) ; extra == 'dev'
